{"wrapper":"div#lookbook-hub-template","sections":{"banner-01":{"type":"banner-01","blocks":{"9a2b5486-eea3-447a-a9ef-1cfaa50ed5a2":{"type":"image","settings":{"image":"shopify:\/\/shop_images\/LOOKBOOK_HUB.png","mobile_image":"shopify:\/\/shop_images\/LOOKBOOK_HUB_3ad8d233-007e-4500-ae9a-cd2b1c9c5eaf.png","heading":"","font_size":48,"font_weight":600,"text_color":"text-dark","text_color_mobile":"text-dark-mobile","text_align_vertical":"center","text_align_horizontal":"center","link":"","button_text":"","font_size_button":25}}},"block_order":["9a2b5486-eea3-447a-a9ef-1cfaa50ed5a2"],"settings":{"section_margin_top":10}},"05e18bc9-400f-4160-b186-8c63b7fe9a5b":{"type":"blog-template-01","settings":{}}},"order":["banner-01","05e18bc9-400f-4160-b186-8c63b7fe9a5b"]}